README.rst
_description.org
lh-agpl3-LICENSE.txt
pyproject.toml
setup.py
bin/gnomeBisos.cs
bin/gnomeCustomize.cs
bisos/__init__.py
bisos.gnome.egg-info/PKG-INFO
bisos.gnome.egg-info/SOURCES.txt
bisos.gnome.egg-info/dependency_links.txt
bisos.gnome.egg-info/not-zip-safe
bisos.gnome.egg-info/requires.txt
bisos.gnome.egg-info/top_level.txt
bisos/gnome/__init__.py
bisos/gnome/gnomeApi.py
bisos/gnome/gnomeBisos.py